tools.py
docx_tools-0.1.0.dist-info/LICENSE
docx_tools-0.1.0.dist-info/METADATA
docx_tools-0.1.0.dist-info/WHEEL
docx_tools-0.1.0.dist-info/top_level.txt
docx_tools-0.1.0.dist-info/RECORD
