Metadata-Version: 2.1
Name: docx-tools
Version: 0.1.0
Summary: A tool for quickly generating word documents based on docx and openpyxl.
Home-page: https://github.com/ldspdvsun/docx-tools
Author: MengYue Sun
Author-email: ldspdvsun@gmail.com
License: MIT
Classifier: License :: OSI Approved :: MIT License
Classifier: Programming Language :: Python
Classifier: Programming Language :: Python :: 3
Classifier: Programming Language :: Python :: 3.6
Classifier: Programming Language :: Python :: Implementation :: CPython
Classifier: Programming Language :: Python :: Implementation :: PyPy
Requires-Python: >=3.6.0
License-File: LICENSE
Requires-Dist: docx
Requires-Dist: openpyxl
